qir_formatter/__init__.py
qir_formatter/labeled_formatter.py
qir_formatter/py.typed
tests/__init__.py
tests/test_qir_formatter.py
qir_formatter-0.1.0.dist-info/METADATA
qir_formatter-0.1.0.dist-info/WHEEL
qir_formatter-0.1.0.dist-info/top_level.txt
qir_formatter-0.1.0.dist-info/RECORD
