Metadata-Version: 2.4
Name: qir-formatter
Version: 0.1.0
Summary: A Python library for QIR Alliance results formatting.
Author-email: Peter Schow <peter.schow@quantinuum.com>, Chester Wringe <chester.wringe@quantinuum.com>
Requires-Python: >=3.10
Requires-Dist: pydantic>=2
